pyserverpilot/__init__.py
pyserverpilot/serverpilot.py
pyserverpilot-1.2.2.dist-info/DESCRIPTION.rst
pyserverpilot-1.2.2.dist-info/METADATA
pyserverpilot-1.2.2.dist-info/RECORD
pyserverpilot-1.2.2.dist-info/WHEEL
pyserverpilot-1.2.2.dist-info/metadata.json
pyserverpilot-1.2.2.dist-info/top_level.txt
